doc2html/__init__.py
doc2html/allocate_unoserver.sh
doc2html/config.py
doc2html/reformat.py
doc2html/schemas.py
doc2html/server.py
doc2html-0.0.1.dist-info/LICENSE
doc2html-0.0.1.dist-info/METADATA
doc2html-0.0.1.dist-info/WHEEL
doc2html-0.0.1.dist-info/top_level.txt
doc2html-0.0.1.dist-info/RECORD
