Metadata-Version: 2.1
Name: doc2html
Version: 0.0.1
Summary: Convert documents between formats. For example docx to html or pdf to html
Author-email: Jose del Rio <jgregrs@yahoo.es>
Maintainer-email: Jose del Rio <jgregrs@yahoo.es>
License: GNU GENERAL PUBLIC LICENSE
Project-URL: Homepage, https://github.com/jgdelrio/doc2html
Project-URL: Documentation, https://github.com/jgdelrio/doc2html
Project-URL: Repository, https://github.com/jgdelrio/doc2html.git
Project-URL: Issues, https://github.com/jgdelrio/doc2html/issues
Keywords: document,transformation,docx,pdf,pptx,html
Classifier: Development Status :: 4 - Beta
Classifier: Intended Audience :: Developers
Classifier: Topic :: Software Development :: Build Tools
Classifier: License :: OSI Approved :: GNU General Public License (GPL)
Classifier: Programming Language :: Python :: 3
Classifier: Programming Language :: Python :: 3.9
Classifier: Programming Language :: Python :: 3.10
Classifier: Programming Language :: Python :: 3.11
Requires-Python: >=3.9
License-File: LICENSE
Requires-Dist: unoserver
Requires-Dist: virtualenv >=20.26.3
Requires-Dist: beautifulsoup4 >=4.12.3
Requires-Dist: mammoth >=1.8.0
Requires-Dist: pdfplumber >=0.11.2
